README.md
setup.py
ProMD.egg-info/PKG-INFO
ProMD.egg-info/SOURCES.txt
ProMD.egg-info/dependency_links.txt
ProMD.egg-info/top_level.txt
promd/__init__.py
promd/markdown.py
promd/nodes.py