Metadata-Version: 2.1
Name: ProMD
Version: 1.0.0
Summary: PMD is a library that contains 
Home-page: https://github.com/ZSendokame/ProMD
Author: ZSendokame
License: MIT license
Platform: UNKNOWN
